[
    {
        "name": "1024", 
        "key":"cao",
        "url": "https://www.t66y.com", 
        "tags": [
            {"name": "DAGER", "url": "http://t66y.com/thread0806.php?fid=16"},
        ], 
        "pages": {
            "element": "body > div.main > table.ajaxtable > tr.tr3 t_one tac > td.tal > h3", 
            "name": {
                "element": "font > a",
                "attr": "@text"
            },
            "url": {
                "element": "a",
                "attr": "href",
                "needMerge": false
            },
            "nextPageUrlMode": {
                "mode": "add", 
                "replaceSearchValue": ".html", 
                "replaceValue": "_{page}.html", 
                "addValue": "{page}.html"
            }, 
            "lastPage": {
                "element": "#pages > a", 
                "minPageLength": 2, 
                "attr": "@text", 
                "descIndex": 2, 
                "isNeedSplit": false, 
                "splits": []
            }
        }, 
        "imgs": {
            "element": "body > div.content > center > img", 
            "nextPageUrlMode": {
                "incrementMode": "page",
                "mode": "replace", 
                "replaceSearchValue": ".html", 
                "replaceValue": "_{page}.html", 
                "addValue": "{page}.html"
            }, 
            "lastPage": {
                "element": "#pages > a", 
                "minPageLength": 2, 
                "attr": "@text", 
                "descIndex": 2, 
                "isNeedSplit": false, 
                "splits": []
            }
        }, 
        "supportReptileVersion": 1
    }
]
